freshen/__init__.py
freshen/console_scripts.py
freshen/modules.py
freshen/reginstall.py
freshen/config/filegroups.yml
freshen_sorter-1.6.3.dist-info/METADATA
freshen_sorter-1.6.3.dist-info/WHEEL
freshen_sorter-1.6.3.dist-info/entry_points.txt
freshen_sorter-1.6.3.dist-info/top_level.txt
freshen_sorter-1.6.3.dist-info/RECORD
