Metadata-Version: 2.1
Name: freshen-sorter
Version: 1.6.3
Summary: A program that sorts files based on various attributes from the (currently only windows) context menu.
Home-page: https://github.com/saleguas/freshen
Author: Salvador Aleguas
Author-email: salvadoraleguas@gmail.com
License: UNKNOWN
Keywords: file,file-organizer,context-menu,file-sorter,sorter
Platform: UNKNOWN
Classifier: Programming Language :: Python :: 3
Classifier: License :: OSI Approved :: MIT License
Classifier: Operating System :: Microsoft :: Windows :: Windows 10
Requires-Python: >=3.6
Requires-Dist: context-menu
Requires-Dist: pyyaml
